{
  "commit_hash": "b55e020684e54bd3d339572f1ef3543be360b6eb",
  "issue_summary": "Early detection that overflow will occur in the variables normalization procedure (\"encode\" method). Warning mentioned in the documentation.",
  "code_before": "public class CMAESOptimizer\n    extends BaseAbstractMultivariateSimpleBoundsOptimizer<MultivariateFunction>\n    implements MultivariateOptimizer {\nprivate void checkParameters() {\n        final double[] init = getStartPoint();\n        final double[] lB = getLowerBound();\n        final double[] uB = getUpperBound();\n        boolean hasFiniteBounds = false;\n        for (int i = 0; i < lB.length; i++) {\n            if (!Double.isInfinite(lB[i]) ||\n                !Double.isInfinite(uB[i])) {\n                hasFiniteBounds = true;\n                break;\n            }\n        }\n        boolean hasInfiniteBounds = false;\n        if (hasFiniteBounds) {\n            for (int i = 0; i < lB.length; i++) {\n                if (Double.isInfinite(lB[i]) ||\n                    Double.isInfinite(uB[i])) {\n                    hasInfiniteBounds = true;\n                    break;\n                }\n            }\n            if (hasInfiniteBounds) {\n                throw new MathUnsupportedOperationException();\n            } else {\n                boundaries = new double[2][];\n                boundaries[0] = lB;\n                boundaries[1] = uB;\n            }\n        } else {\n            boundaries = null;\n        }\n        if (inputSigma != null) {\n            if (inputSigma.length != init.length) {\n                throw new DimensionMismatchException(inputSigma.length, init.length);\n            }\n            for (int i = 0; i < init.length; i++) {\n                if (inputSigma[i] < 0) {\n                    throw new NotPositiveException(inputSigma[i]);\n                }\n                if (boundaries != null) {\n                    if (inputSigma[i] > boundaries[1][i] - boundaries[0][i]) {\n                        throw new OutOfRangeException(inputSigma[i], 0, boundaries[1][i] - boundaries[0][i]);\n                    }\n                }\n            }\n        }\n    }\n}",
  "code_after": "public class CMAESOptimizer\n    extends BaseAbstractMultivariateSimpleBoundsOptimizer<MultivariateFunction>\n    implements MultivariateOptimizer {\nprivate void checkParameters() {\n        final double[] init = getStartPoint();\n        final double[] lB = getLowerBound();\n        final double[] uB = getUpperBound();\n        boolean hasFiniteBounds = false;\n        for (int i = 0; i < lB.length; i++) {\n            if (!Double.isInfinite(lB[i]) ||\n                !Double.isInfinite(uB[i])) {\n                hasFiniteBounds = true;\n                break;\n            }\n        }\n        boolean hasInfiniteBounds = false;\n        if (hasFiniteBounds) {\n            for (int i = 0; i < lB.length; i++) {\n                if (Double.isInfinite(lB[i]) ||\n                    Double.isInfinite(uB[i])) {\n                    hasInfiniteBounds = true;\n                    break;\n                }\n            }\n            if (hasInfiniteBounds) {\n                throw new MathUnsupportedOperationException();\n            } else {\n                boundaries = new double[2][];\n                boundaries[0] = lB;\n                boundaries[1] = uB;\n                for (int i = 0; i < lB.length; i++) {\n                    if (Double.isInfinite(boundaries[1][i] - boundaries[0][i])) {\n                        final double max = Double.MAX_VALUE + boundaries[0][i];\n                        final NumberIsTooLargeException e\n                            = new NumberIsTooLargeException(boundaries[1][i],\n                                                            max,\n                                                            true);\n                        e.getContext().addMessage(LocalizedFormats.OVERFLOW);\n                        e.getContext().addMessage(LocalizedFormats.INDEX, i);\n                        throw e;\n                    }\n                }\n            }\n        } else {\n            boundaries = null;\n        }\n        if (inputSigma != null) {\n            if (inputSigma.length != init.length) {\n                throw new DimensionMismatchException(inputSigma.length, init.length);\n            }\n            for (int i = 0; i < init.length; i++) {\n                if (inputSigma[i] < 0) {\n                    throw new NotPositiveException(inputSigma[i]);\n                }\n                if (boundaries != null) {\n                    if (inputSigma[i] > boundaries[1][i] - boundaries[0][i]) {\n                        throw new OutOfRangeException(inputSigma[i], 0, boundaries[1][i] - boundaries[0][i]);\n                    }\n                }\n            }\n        }\n    }\n}",
  "javadoc_before": "/**\n * <p>An implementation of the active Covariance Matrix Adaptation Evolution Strategy (CMA-ES)\n * for non-linear, non-convex, non-smooth, global function minimization.\n * The CMA-Evolution Strategy (CMA-ES) is a reliable stochastic optimization method\n * which should be applied if derivative-based methods, e.g. quasi-Newton BFGS or\n * conjugate gradient, fail due to a rugged search landscape (e.g. noise, local\n * optima, outlier, etc.) of the objective function. Like a\n * quasi-Newton method, the CMA-ES learns and applies a variable metric\n * on the underlying search space. Unlike a quasi-Newton method, the\n * CMA-ES neither estimates nor uses gradients, making it considerably more\n * reliable in terms of finding a good, or even close to optimal, solution.</p>\n *\n * <p>In general, on smooth objective functions the CMA-ES is roughly ten times\n * slower than BFGS (counting objective function evaluations, no gradients provided).\n * For up to <math>N=10</math> variables also the derivative-free simplex\n * direct search method (Nelder and Mead) can be faster, but it is\n * far less reliable than CMA-ES.</p>\n *\n * <p>The CMA-ES is particularly well suited for non-separable\n * and/or badly conditioned problems. To observe the advantage of CMA compared\n * to a conventional evolution strategy, it will usually take about\n * <math>30 N</math> function evaluations. On difficult problems the complete\n * optimization (a single run) is expected to take <em>roughly</em> between\n * <math>30 N</math> and <math>300 N<sup>2</sup></math>\n * function evaluations.</p>\n *\n * <p>This implementation is translated and adapted from the Matlab version\n * of the CMA-ES algorithm as implemented in module {@code cmaes.m} version 3.51.</p>\n *\n * For more information, please refer to the following links:\n * <ul>\n *  <li><a href=\"http://www.lri.fr/~hansen/cmaes.m\">Matlab code</a></li>\n *  <li><a href=\"http://www.lri.fr/~hansen/cmaesintro.html\">Introduction to CMA-ES</a></li>\n *  <li><a href=\"http://en.wikipedia.org/wiki/CMA-ES\">Wikipedia</a></li>\n * </ul>\n *\n * @version $Id$\n * @since 3.0\n */",
  "javadoc_after": "/**\n * <p>An implementation of the active Covariance Matrix Adaptation Evolution Strategy (CMA-ES)\n * for non-linear, non-convex, non-smooth, global function minimization.\n * The CMA-Evolution Strategy (CMA-ES) is a reliable stochastic optimization method\n * which should be applied if derivative-based methods, e.g. quasi-Newton BFGS or\n * conjugate gradient, fail due to a rugged search landscape (e.g. noise, local\n * optima, outlier, etc.) of the objective function. Like a\n * quasi-Newton method, the CMA-ES learns and applies a variable metric\n * on the underlying search space. Unlike a quasi-Newton method, the\n * CMA-ES neither estimates nor uses gradients, making it considerably more\n * reliable in terms of finding a good, or even close to optimal, solution.</p>\n *\n * <p>In general, on smooth objective functions the CMA-ES is roughly ten times\n * slower than BFGS (counting objective function evaluations, no gradients provided).\n * For up to <math>N=10</math> variables also the derivative-free simplex\n * direct search method (Nelder and Mead) can be faster, but it is\n * far less reliable than CMA-ES.</p>\n *\n * <p>The CMA-ES is particularly well suited for non-separable\n * and/or badly conditioned problems. To observe the advantage of CMA compared\n * to a conventional evolution strategy, it will usually take about\n * <math>30 N</math> function evaluations. On difficult problems the complete\n * optimization (a single run) is expected to take <em>roughly</em> between\n * <math>30 N</math> and <math>300 N<sup>2</sup></math>\n * function evaluations.</p>\n *\n * <p>This implementation is translated and adapted from the Matlab version\n * of the CMA-ES algorithm as implemented in module {@code cmaes.m} version 3.51.</p>\n *\n * For more information, please refer to the following links:\n * <ul>\n *  <li><a href=\"http://www.lri.fr/~hansen/cmaes.m\">Matlab code</a></li>\n *  <li><a href=\"http://www.lri.fr/~hansen/cmaesintro.html\">Introduction to CMA-ES</a></li>\n *  <li><a href=\"http://en.wikipedia.org/wiki/CMA-ES\">Wikipedia</a></li>\n * </ul>\n *\n * When simple constraints (boundaries) are used, care must be taken that the\n * difference between the upper and lower bounds does not overflow; should it\n * be the case, a {@link NumberIsTooLargeException} will be thrown by the\n * {@link BaseAbstractMultivariateSimpleBoundsOptimizer#optimize(int,\n * MultivariateFunction,GoalType,double[],double[],double[]) optimize} method.\n *\n * @version $Id$\n * @since 3.0\n */"
}