{
  "commit_hash": "16acabd53f938735aae79bf7428359b68afea88b",
  "issue_summary": "Add new NaNStrategy FAILED, thanks to Patrick Meyer.",
  "code_before": "public double[] rank(double[] data) {\n\n        // Array recording initial positions of data to be ranked\n        IntDoublePair[] ranks = new IntDoublePair[data.length];\n        for (int i = 0; i < data.length; i++) {\n            ranks[i] = new IntDoublePair(data[i], i);\n        }\n\n        // Recode, remove or record positions of NaNs\n        List<Integer> nanPositions = null;\n        switch (nanStrategy) {\n            case MAXIMAL: // Replace NaNs with +INFs\n                recodeNaNs(ranks, Double.POSITIVE_INFINITY);\n                break;\n            case MINIMAL: // Replace NaNs with -INFs\n                recodeNaNs(ranks, Double.NEGATIVE_INFINITY);\n                break;\n            case REMOVED: // Drop NaNs from data\n                ranks = removeNaNs(ranks);\n                break;\n            case FIXED:   // Record positions of NaNs\n                nanPositions = getNanPositions(ranks);\n                break;\n            default: // this should not happen unless NaNStrategy enum is changed\n                throw new MathInternalError();\n        }\n\n        // Sort the IntDoublePairs\n        Arrays.sort(ranks);\n\n        // Walk the sorted array, filling output array using sorted positions,\n        // resolving ties as we go\n        double[] out = new double[ranks.length];\n        int pos = 1;  // position in sorted array\n        out[ranks[0].getPosition()] = pos;\n        List<Integer> tiesTrace = new ArrayList<Integer>();\n        tiesTrace.add(ranks[0].getPosition());\n        for (int i = 1; i < ranks.length; i++) {\n            if (Double.compare(ranks[i].getValue(), ranks[i - 1].getValue()) > 0) {\n                // tie sequence has ended (or had length 1)\n                pos = i + 1;\n                if (tiesTrace.size() > 1) {  // if seq is nontrivial, resolve\n                    resolveTie(out, tiesTrace);\n                }\n                tiesTrace = new ArrayList<Integer>();\n                tiesTrace.add(ranks[i].getPosition());\n            } else {\n                // tie sequence continues\n                tiesTrace.add(ranks[i].getPosition());\n            }\n            out[ranks[i].getPosition()] = pos;\n        }\n        if (tiesTrace.size() > 1) {  // handle tie sequence at end\n            resolveTie(out, tiesTrace);\n        }\n        if (nanStrategy == NaNStrategy.FIXED) {\n            restoreNaNs(out, nanPositions);\n        }\n        return out;\n    }",
  "code_after": "public double[] rank(double[] data) {\n\n        // Array recording initial positions of data to be ranked\n        IntDoublePair[] ranks = new IntDoublePair[data.length];\n        for (int i = 0; i < data.length; i++) {\n            ranks[i] = new IntDoublePair(data[i], i);\n        }\n\n        // Recode, remove or record positions of NaNs\n        List<Integer> nanPositions = null;\n        switch (nanStrategy) {\n            case MAXIMAL: // Replace NaNs with +INFs\n                recodeNaNs(ranks, Double.POSITIVE_INFINITY);\n                break;\n            case MINIMAL: // Replace NaNs with -INFs\n                recodeNaNs(ranks, Double.NEGATIVE_INFINITY);\n                break;\n            case REMOVED: // Drop NaNs from data\n                ranks = removeNaNs(ranks);\n                break;\n            case FIXED:   // Record positions of NaNs\n                nanPositions = getNanPositions(ranks);\n                break;\n            case FAILED:\n                nanPositions = getNanPositions(ranks);\n                if (nanPositions.size() > 0) {\n                    throw new NotANumberException();\n                }\n                break;\n            default: // this should not happen unless NaNStrategy enum is changed\n                throw new MathInternalError();\n        }\n\n        // Sort the IntDoublePairs\n        Arrays.sort(ranks);\n\n        // Walk the sorted array, filling output array using sorted positions,\n        // resolving ties as we go\n        double[] out = new double[ranks.length];\n        int pos = 1;  // position in sorted array\n        out[ranks[0].getPosition()] = pos;\n        List<Integer> tiesTrace = new ArrayList<Integer>();\n        tiesTrace.add(ranks[0].getPosition());\n        for (int i = 1; i < ranks.length; i++) {\n            if (Double.compare(ranks[i].getValue(), ranks[i - 1].getValue()) > 0) {\n                // tie sequence has ended (or had length 1)\n                pos = i + 1;\n                if (tiesTrace.size() > 1) {  // if seq is nontrivial, resolve\n                    resolveTie(out, tiesTrace);\n                }\n                tiesTrace = new ArrayList<Integer>();\n                tiesTrace.add(ranks[i].getPosition());\n            } else {\n                // tie sequence continues\n                tiesTrace.add(ranks[i].getPosition());\n            }\n            out[ranks[i].getPosition()] = pos;\n        }\n        if (tiesTrace.size() > 1) {  // handle tie sequence at end\n            resolveTie(out, tiesTrace);\n        }\n        if (nanStrategy == NaNStrategy.FIXED) {\n            restoreNaNs(out, nanPositions);\n        }\n        return out;\n    }",
  "javadoc_before": "/**\n     * Rank <code>data</code> using the natural ordering on Doubles, with\n     * NaN values handled according to <code>nanStrategy</code> and ties\n     * resolved using <code>tiesStrategy.</code>\n     *\n     * @param data array to be ranked\n     * @return array of ranks\n     */",
  "javadoc_after": "/**\n     * Rank <code>data</code> using the natural ordering on Doubles, with\n     * NaN values handled according to <code>nanStrategy</code> and ties\n     * resolved using <code>tiesStrategy.</code>\n     *\n     * @param data array to be ranked\n     * @return array of ranks\n     * @throws NotANumberException if the selected {@link NaNStrategy} is {@code FAILED}\n     * and a {@link Double#NaN} is encountered in the input data\n     */"
}