{
  "commit_hash": "75dd5e9f9e13c72890f1e5b1695f8281fe990d94",
  "issue_summary": "IndexableField.tokenStream() no longer throws IOException",
  "code_before": "public TokenStream tokenStream(Analyzer analyzer, TokenStream reuse) throws IOException;",
  "code_after": "public TokenStream tokenStream(Analyzer analyzer, TokenStream reuse);",
  "javadoc_before": "/**\n   * Creates the TokenStream used for indexing this field.  If appropriate,\n   * implementations should use the given Analyzer to create the TokenStreams.\n   *\n   * @param analyzer Analyzer that should be used to create the TokenStreams from\n   * @param reuse TokenStream for a previous instance of this field <b>name</b>. This allows\n   *              custom field types (like StringField and NumericField) that do not use\n   *              the analyzer to still have good performance. Note: the passed-in type\n   *              may be inappropriate, for example if you mix up different types of Fields\n   *              for the same field name. So it's the responsibility of the implementation to\n   *              check.\n   * @return TokenStream value for indexing the document.  Should always return\n   *         a non-null value if the field is to be indexed\n   * @throws IOException Can be thrown while creating the TokenStream\n   */",
  "javadoc_after": "/**\n   * Creates the TokenStream used for indexing this field.  If appropriate,\n   * implementations should use the given Analyzer to create the TokenStreams.\n   *\n   * @param analyzer Analyzer that should be used to create the TokenStreams from\n   * @param reuse TokenStream for a previous instance of this field <b>name</b>. This allows\n   *              custom field types (like StringField and NumericField) that do not use\n   *              the analyzer to still have good performance. Note: the passed-in type\n   *              may be inappropriate, for example if you mix up different types of Fields\n   *              for the same field name. So it's the responsibility of the implementation to\n   *              check.\n   * @return TokenStream value for indexing the document.  Should always return\n   *         a non-null value if the field is to be indexed\n   */"
}