{
  "commit_hash": "5e61ac9bf1836c7c33a36b8e221bf5abaa80a8b7",
  "issue_summary": "gdata update",
  "code_before": "public StorageCoreController() throws IOException, StorageException {\n        synchronized (StorageCoreController.class) {\n        \tthis.closeCondition = this.storageControllerLock.newCondition();\n            try {\n                this.idGenerator = new IDGenerator(10);\n            } catch (Exception e) {\n                throw new StorageException(\"Can't create ID Generator\", e);\n            }\n\n            boolean createNewStorage = false;\n            this.configurator = StorageConfigurator.getStorageConfigurator();\n            if (!this.configurator.isRamDirectory()) {\n\n                String storageDirPath = this.configurator.getStorageDirectory();\n                File storeDir = new File(storageDirPath);\n                File storageLog = new File(storeDir.getAbsolutePath()\n                        + System.getProperty(\"file.separator\") + STORAGELOG);\n                try {\n                    if (storeDir.isDirectory() && !storageLog.exists()) {\n\n                        if (createLuceneStorageLog(storeDir)) {\n                            this.storageDir = FSDirectory.getDirectory(\n                                    storeDir, true);\n                            createNewStorage = true;\n                        } else\n                            throw new StorageException(\n                                    \"could not create storage lock file in \"\n                                            + storageDirPath);\n\n                    } else\n                        this.storageDir = FSDirectory.getDirectory(storeDir,\n                                false);\n                } catch (IOException e) {\n                    storageLog.delete();\n                    throw e;\n                }\n                this.indexOptimizeInterval = this.configurator\n                        .getIndexOptimizeInterval();\n                this.storageBufferSize = this.configurator\n                        .getStorageBufferSize() < DEFAULT_STORAGE_BUFFER_SIZE ? DEFAULT_STORAGE_BUFFER_SIZE\n                        : this.configurator.getStorageBufferSize();\n                this.storagePersistFactor = this.configurator\n                        .getStoragepersistFactor() < DEFAULT_STORAGE_PERSIST_FACTOR ? DEFAULT_STORAGE_PERSIST_FACTOR\n                        : this.configurator.getStoragepersistFactor();\n\n            } else\n                this.storageDir = getRamDirectory();\n\n            this.currentBuffer = new StorageBuffer(this.storageBufferSize);\n            this.modifier = createStorageModifier(createNewStorage);\n            this.searcher = new IndexSearcher(this.storageDir);\n//            this.recoverController = new RecoverController(null,this.configurator.isRecover(),this.configurator.isKeepRecoveredFiles());\n            if(createNewStorage)\n                createAdminAccount();\n\n        }\n\n    }",
  "code_after": "public StorageCoreController() {\n        this.closeCondition = this.storageControllerLock.newCondition();\n        this.storageLock = SingleHostConcurrentStorageLock.getConcurrentStorageLock();\n\n    }",
  "javadoc_before": "/**\n     * Creates a new <tt>StoragCoreController</tt> and sets up the storage\n     * environment reading the configuration file.\n     * \n     * \n     * \n     * @throws IOException -\n     *             if an IOException occures\n     * @throws StorageException -\n     *             if the storage lock can not be created or the\n     *             {@link IDGenerator} can not be loaded\n     */",
  "javadoc_after": "/**\n     * Creates a new <tt>StoragCoreController</tt>\n     */"
}